magichue/__init__.py
magichue/bulb_types.py
magichue/commands.py
magichue/discover.py
magichue/magichue.py
magichue/modes.py
magichue/utils.py
magichue-0.2.9.2.dist-info/LICENSE
magichue-0.2.9.2.dist-info/METADATA
magichue-0.2.9.2.dist-info/WHEEL
magichue-0.2.9.2.dist-info/top_level.txt
magichue-0.2.9.2.dist-info/RECORD
